functions_by_maryK03/README.md
functions_by_maryK03/math_functions.py
functions_by_maryk03-0.3.0.dist-info/WHEEL
functions_by_maryk03-0.3.0.dist-info/METADATA
functions_by_maryk03-0.3.0.dist-info/RECORD
